{
    "index": {
        "banner": [
            {
                "id": 1,
                "title": "少量多樣<br>已是接單常態",
                "desc": "●客製化訂單時代來臨,公司營運策略如何因應?<br>●生產規劃、存貨政策、採購策略、產品開發...的挑戰在那裡?",
                "imgSrc": "images/index/hero-bg1.jpg",
                "url": "javascript:;"
            },
            {
                "id": 2,
                "title": "電子業轉型<br>車用,交通,醫療...<br>已是趨勢",
                "desc": "●搶進新市場的背後,企業內部需要作那些改變?<br>●通過TS-16949、ISO-13485，真正的挑戰才正要開始?",
                "imgSrc": "images/index/hero-bg2.jpg",
                "url": "javascript:;"
            },
            {
                "id": 3,
                "title": "擁抱智慧製造<br>勾勒最佳路徑",
                "subtitle": "贏在生產力4.0",
                "desc": "邁向智慧製造阻力最小之路",
                "imgSrc": "images/index/hero-bg3.jpg",
                "url": "javascript:;"
            }
        ],
        "section1": [
            {
                "link": "solution/01",
                "figcaption": "電子零組件"
            },
            {
                "link": "solution/02",
                "figcaption": "電子組裝業"
            },
            {
                "link": "solution/03",
                "figcaption": "連接器"
            },
            {
                "link": "solution/04",
                "figcaption": "電池製造"
            },
            {
                "link": "solution/05",
                "figcaption": "太陽能"
            },
            {
                "link": "solution/06",
                "figcaption": "LED"
            },
            {
                "link": "solution/07",
                "figcaption": "PCB"
            },
            {
                "link": "solution/08",
                "figcaption": "IC設計"
            }
        ],
        "section2": [
            {
                "link": "https://www.digiwin.com/softwareDetail_P201211123807.html",
                "text": "電子表單(ASP版)"
            },
            {
                "link": "https://www.digiwin.com/softwareDetail_P201211123807.html",
                "text": "企業流程管理BPM"
            },
            {
                "link": "https://www.digiwin.com/softwareDetail_P201402131102.html",
                "text": "人力資源HR"
            },
            {
                "link": "https://www.digiwin.com/softwareDetail_P201402133996.html",
                "text": "先進規劃與排程APS"
            },
            {
                "link": "https://www.digiwin.com/softwareDetail_P201402135005.html",
                "text": "廠區生產追蹤SFT"
            },
            {
                "link": "https://www.digiwin.com/softwareDetail_P2012111241110.html",
                "text": "Portal"
            },
            {
                "link": "http://www.dsc.com.tw/event/WB002323/WB00232301.html",
                "text": "專案成本"
            },
            {
                "link": "https://www.digiwin.com/tw/dsc/solution/WB002513/WB00251301?tag#contact",
                "text": "廠務管理"
            },
            {
                "link": "https://www.digiwin.com/softwareDetail_P2012111250711.html",
                "text": "商業智慧BI"
            },
            {
                "link": "https://www.digiwin.com/softwareDetail_P201211123618.html",
                "text": "客戶關係管理CRM"
            },
            {
                "link": "https://www.digiwin.com/softwareDetail_P201404098942.html",
                "text": "產品生命週期PLM"
            },
            {
                "link": "https://www.digiwin.com/softwareDetail_P201510069182.html",
                "text": "MES"
            },
            {
                "link": "https://www.digiwin.com/softwareDetail_P201404149431.html",
                "text": "Mobile Solution"
            },
            {
                "link": "https://www.digiwin.com/softwareDetail_P201402139004.html",
                "text": "供應鏈管理EC"
            },
            {
                "link": "https://www.digiwin.com/tw/dsc/solution/WB002513/WB00251301?tag#contact",
                "text": "產品溯源"
            },
            {
                "link": "https://www.digiwin.com/tw/dsc/solution/WB002513/WB00251301?tag#contact",
                "text": "CQA"
            }
        ],
        "slides": [
            {
                "video": "https://www.youtube.com/embed/H_XO3fwT0F8",
                "company": "信邦<br>電子",
                "people": "王紹新 董事長",
                "content": "轉型創新沒有捷徑，因為機會只留給準備好的人！時存危機感將引領企業邁向成功，且最重要的關鍵就是：要能夠捨得！"
            },
            {
                "video": "https://www.youtube.com/embed/0dPtb5mFa8Y",
                "company": "創譽<br>科技",
                "people": "應國良 總經理",
                "content": "系統上線第二個月系統版和人工版的數據幾乎完全一致，生管負擔減少許多；人均產值、生產效率和訂單達交率更有明顯提升！"
            },
            {
                "video": "https://www.youtube.com/embed/0U0kU-CSEGo",
                "company": "茂寧<br>企業",
                "people": "薛聰義 經理",
                "content": "採購物料計劃改用APS系統後，生管在八小時內就能夠完成原本的工作項目。寧茂企業 快速回應機制提升客戶服務滿意度！"
            }
        ]
    },
    "issue01": {
        "banner": [
            {
                "id": 1,
                "title": "當<strong>大量客製化</strong><br>時代來臨,<br><strong>少量多樣</strong>運作模式<br>成為常態",
                "desc": "電子業如何解決產品變多元, 小量採購, 庫存管理, 交貨速度, 小批量生產, 換線換模頻繁，生產效率大幅下降?……交期與存貨非得二難不可嗎?",
                "imgSrc": "images/issue01/hero-bg.jpg",
                "url": "javascript:;"
            }
        ],
        "section3": [
            "料號大幅增長，引起產品及<br>工程管理作業的負擔加重",
            "需求批量變小，引發現場<br>設備稼動及交期滿足的衝突加劇",
            "多種原料需求，導致採購批量<br>與存貨囤積風險間的取捨",
            "訂單筆數擴張，造成產銷規畫<br>及協調複雜度的快速提升",
            "規格多元發展，促使庫存品項<br>及存貨水位的快速增加",
            "產品組合增多，提升產品獲利<br>分析需求的作業成本及難度"
        ],
        "slides": [
            {
                "id": 1,
                "title": "運用<品號管理><br>降低交易複雜",
                "subtitle": "強化品號管理制度",
                "list": [
                    {
                        "term": "方案",
                        "desc": "梳理少量多樣訂單，所產生的品號複雜度"
                    },
                    {
                        "term": "步驟",
                        "desc": "● 建立標準的編碼原則規範，合理規劃物料分類，實現自動編碼的標準化<br>● 利用品號特徵碼及組合管理因應"
                    },
                    {
                        "term": "改變",
                        "desc": "不再因為客製化產品，造成編列品號的繁瑣度"
                    },
                    {
                        "term": "影響",
                        "desc": "● 結構清楚，維護便利，減少出錯<br>● 簡化大量品號的建置"
                    }
                ],
                "imgSrc": "images/issue01/section4-slide1.png"
            },
            {
                "id": 2,
                "title": "善用<模組化設計><br>提升產品配置彈性",
                "subtitle": "彈性化的模組規劃設計",
                "list": [
                    {
                        "term": "方案",
                        "desc": "少量多樣的訂單需求，利用模組化配置彈性，即時的回應"
                    },
                    {
                        "term": "步驟",
                        "desc": "● 建立標準化設計小組，設置新產品專案管理的標準化準則<br>● 因應ATO(assemble to order)CTO(configure to order)的接單模式，實現客戶需求BOM自動產生"
                    },
                    {
                        "term": "改變",
                        "desc": "客製化BOM設計模式和步驟更為規範"
                    },
                    {
                        "term": "影響",
                        "desc": "● 釋放工程人員瓶頸，快速回應客戶，精準傳遞配置資訊<br>● 加速BOM設計與製造的轉換時間"
                    }
                ],
                "imgSrc": "images/issue01/section4-slide2.png"
            },
            {
                "list": [
                    "3. 強化即時製程掌控與進度管理",
                    "4. 建置快速反應的計劃與排程能力",
                    "5. 調整及修正採購策略及備貨模式",
                    "6. 審視及建構合宜的存貨政策",
                    "7. 重新思考製造現場的績效追求",
                    "8. 精細化的成本歸屬及產品利潤管理"
                ]
            }
        ],
        "caseList": [
            {
                "link": "/tw/case/784.html",
                "company": "致威電子",
                "desc": "少量多樣的市場需求，形成「一圖對多料」及「料件與圖面無直接關聯」的情況…"
            },
            {
                "link": "/tw/case/818.html",
                "company": "微鑫電子",
                "desc": "原有紙本作業已無法負擔少量多樣的­市場趨勢…"
            },
            {
                "link": "/caseListDetail.aspx?id=6581",
                "company": "吉鴻電子",
                "desc": "產品少量多樣化，客製需求大，無論軟、硬體、機構皆自力研發…"
            },
            {
                "link": "/tw/case/1047.html",
                "company": "崧柏電子",
                "desc": "產業特性『少量多樣』，圖資大量的產生…"
            },
            {
                "link": "/tw/case/1016.html",
                "company": "研騰科技",
                "desc": "一般少量多樣的客戶走的都是高階路線，對產品的品質要求很高…"
            }
        ]
    },
    "seminar": {
        "title": "研討會",
        "section1Title": "系列研討會，挑戰少量多樣的生產衝擊",
        "section1Desc": "鼎新為電子業舉辦各式管理議題與實務操作兼俱的研討會，如您在過去因工作繁忙無法親臨參加，我們將提供免費講義資料索取….期許與您在產業快速變化的年代，一同吸收新知，一同改變與成長…"
    },
    "solution": {
        "banner": [
            {
                "id": 1,
                "title": "title",
                "desc": "desc",
                "imgSrc": "images/solution/hero-bg.jpg",
                "url": "javascript:;"
            }
        ]
    },
    "wall": {
        "banner": [
            {
                "id": 1,
                "title": "title",
                "desc": "desc",
                "imgSrc": "images/wall/hero-bg.jpg",
                "url": "javascript:;"
            }
        ]
    }
}